file_writer/__init__.py
file_writer/file_writer.py
file_writer/file_writer_manager.py
file_writer/merged_dicts.py
file_writer/cli/__init__.py
file_writer/cli/launch.py
file_writer_plugins/__init__.py
file_writer_plugins/cSAXS.py
file_writer_plugins/default_writer.py
bec_file_writer-1.24.1.dist-info/METADATA
bec_file_writer-1.24.1.dist-info/WHEEL
bec_file_writer-1.24.1.dist-info/entry_points.txt
bec_file_writer-1.24.1.dist-info/top_level.txt
bec_file_writer-1.24.1.dist-info/RECORD
