Metadata-Version: 2.1
Name: bec-file-writer
Version: 1.24.1
Summary: BEC service for writing metadata files
Home-page: https://gitlab.psi.ch/bec/bec
Project-URL: Bug Tracker, https://gitlab.psi.ch/bec/bec/issues
Classifier: Programming Language :: Python :: 3
Classifier: Development Status :: 3 - Alpha
Classifier: Topic :: Scientific/Engineering
Requires-Python: >=3.10
Requires-Dist: numpy
Requires-Dist: pyyaml
Requires-Dist: h5py
Requires-Dist: xmltodict
Requires-Dist: bec-lib
Provides-Extra: dev
Requires-Dist: pytest ; extra == 'dev'
Requires-Dist: pytest-random-order ; extra == 'dev'
Requires-Dist: coverage ; extra == 'dev'
Requires-Dist: black ; extra == 'dev'
Requires-Dist: isort ; extra == 'dev'
Requires-Dist: pylint ; extra == 'dev'
